ALPC/Character.py
ALPC/Constants.py
ALPC/Delaunator.py
ALPC/Entity.py
ALPC/Game.py
ALPC/Mage.py
ALPC/Merchant.py
ALPC/Observer.py
ALPC/Paladin.py
ALPC/Pathfinder.py
ALPC/PingCompensatedCharacter.py
ALPC/Player.py
ALPC/Priest.py
ALPC/Ranger.py
ALPC/Rogue.py
ALPC/Tools.py
ALPC/Warrior.py
ALPC/__init__.py
ALPC/database/Database.py
ALPC/database/Schemas.py
ALPC/database/__init__.py
ALPC/psSocketIO/__init__.py
ALPC/psSocketIO/asyncio_client.py
ALPC/psSocketIO/client.py
ALPC/psSocketIO/exceptions.py
ALPC/psSocketIO/namespace.py
ALPC/psSocketIO/packet.py
ALPC-0.4.0.dist-info/LICENSE
ALPC-0.4.0.dist-info/METADATA
ALPC-0.4.0.dist-info/WHEEL
ALPC-0.4.0.dist-info/top_level.txt
ALPC-0.4.0.dist-info/RECORD
