Metadata-Version: 2.1
Name: ALPC
Version: 0.4.0
Summary: A python client for AdventureLand.
Home-page: https://github.com/StormSurge95/ALPC
Author: Storm Cassidy
License: GNU General Public License v3 (GPLv3)
Project-URL: Bug Tracker, https://github.com/StormSurge95/ALPC/issues
Classifier: Programming Language :: Python :: 3
Classifier: License :: OSI Approved :: GNU General Public License v3 (GPLv3)
Classifier: Operating System :: OS Independent
Requires-Python: >=3.10.4
License-File: LICENSE
